pykaiutils/__init__.py
pykaiutils/runTime.py
pykaiutils/decorator/__init__.py
pykaiutils/decorator/check.py
pykaiutils/decorator/runTime.py
pykaiutils/decorator/timer.py
pykaiutils-0.0.4.dist-info/METADATA
pykaiutils-0.0.4.dist-info/RECORD
pykaiutils-0.0.4.dist-info/WHEEL
pykaiutils-0.0.4.dist-info/top_level.txt
