Metadata-Version: 2.1
Name: pykaiutils
Version: 0.0.4
Summary: Python wrapper for pykaiutils: python开发中常用的代码结构库
Home-page: https://github.com/pypi/sampleproject
Author: 贾志凯
Author-email: 15716539228@163.com
License: UNKNOWN
Platform: UNKNOWN
Classifier: Programming Language :: Python :: 3.6
Classifier: License :: OSI Approved :: MIT License
Classifier: Operating System :: OS Independent
License-File: LICENSE
